ocsh/__init__.py
ocsh/config.py
ocsh/main.py
ocsh/cli/__init__.py
ocsh/cli/main.py
ocsh/handlers/__init__.py
ocsh/handlers/base_handler.py
ocsh/handlers/oss.py
octopus_cloud_storage_hub-0.1.6.dist-info/METADATA
octopus_cloud_storage_hub-0.1.6.dist-info/WHEEL
octopus_cloud_storage_hub-0.1.6.dist-info/entry_points.txt
octopus_cloud_storage_hub-0.1.6.dist-info/RECORD
