Metadata-Version: 2.4
Name: octopus-cloud-storage-hub
Version: 0.1.6
Summary: Octopus Cloud Storage Hub
Requires-Python: >=3.11
Requires-Dist: build>=1.2.2.post1
Requires-Dist: click<8.2.0
Requires-Dist: oss2>=2.19.1
Requires-Dist: python-dotenv==1.0.1
Requires-Dist: rich==13.7.1
Requires-Dist: twine>=6.1.0
Requires-Dist: typer>=0.15.3
